libspatialindex/__init__.py
libspatialindex-11.0.2.dist-info/licenses/LICENSE
libspatialindex-11.0.2.dist-info/METADATA
libspatialindex-11.0.2.dist-info/WHEEL
libspatialindex-11.0.2.dist-info/top_level.txt
libspatialindex-11.0.2.dist-info/RECORD
